{
  "episodes": {
    "主线路": "https://player.putaoplayer.com:166/20230310/E7E2FF7C76E639CB/hls/1000k/index.m3u8"
  },
  "seriesInfo": {
    "id": 100061,
    "IDcode": "APKH-024",
    "title": "ヤリ部屋に連れ込まれた天使 幼気なJKは、屈辱的な仕打ちに萌えて、愛液を迸らせながら超悶絶！ 宮崎あや",
    "publish_date": "2016-11-13",
    "type": "有码",
    "company": null,
    "genres": [
      "高中女生",
      "中出",
      "第一人称摄影",
      "颜射",
      "调教"
    ],
    "description": "",
    "cover_url": "https://cdn4.aiscan.cc/theme/javmenu/images/loading.gif",
    "background_img": null,
    "title_play_url": "https://erik7761269084-arch.github.io/-/JAV/player_template.html?series=100061",
    "actresses": [
      {
        "name": "宫崎彩",
        "img_url": "https://picture.yoshiclub.xyz/20230701/5391bf25-c850-4c23-8f3b-e8947519f2bd.jpg",
        "profile_url": "https://erik7761269084-arch.github.io/-/AV/AVactressDatas.html?series=100061&name=宫崎彩"
      }
    ]
  }
}