{
  "episodes": {
    "主线路": "https://player.putaoplayer.com:166/20230312/AAC71809512EC8AD/hls/1000k/index.m3u8"
  },
  "seriesInfo": {
    "id": 100125,
    "IDcode": "FONE-082",
    "title": "生徒会長は巨乳で小悪魔な痴女リータ ダメ教師撲滅×学校浄化大作戦----",
    "publish_date": "2019-09-12",
    "type": "有码",
    "company": null,
    "genres": [
      "高中女生",
      "巨乳",
      "中出",
      "荡妇",
      "美少女电影",
      "素人作品"
    ],
    "description": null,
    "cover_url": "https://pics.dmm.co.jp/mono/movie/adult/h_491fone082/h_491fone082pl.jpg",
    "background_img": null,
    "title_play_url": "https://erik7761269084-arch.github.io/-/JAV/player_template.html?series=100125",
    "actresses": [
      {
        "name": "森本つぐみ",
        "img_url": "",
        "profile_url": "https://erik7761269084-arch.github.io/-/AV/AVactressDatas.html?series=100125&name=森本つぐみ"
      }
    ]
  }
}