{
  "episodes": {
    "主线路": "https://vz-a59c6881-d86.b-cdn.net/ce6dcd30-11e6-4e9e-beb8-9ee6afcf559e/playlist.m3u8"
  },
  "seriesInfo": {
    "id": 499,
    "IDcode": "HEYZO-0597",
    "title": "集團顏射！可愛的蘿莉女生被強奸 淫蒎學園的背德事件薄 ~ 伊澄知世",
    "publish_date": "2014-05-18",
    "type": "无码",
    "company": "HEYZO",
    "genres": [
      "後入",
      "69",
      "劇情",
      "淫亂",
      "變態",
      "校花",
      "凌辱",
      "中出",
      "女上位",
      "JK校服",
      "潮吹",
      "顏射",
      "口交",
      "強姦",
      "騎乗位",
      "白絲",
      "少女",
      "蘿莉控",
      "美少女",
      "清楚系",
      "清純",
      "校園生活",
      "手指插入",
      "M男・M女",
      "學校",
      "短髮",
      "美少女電影",
      "女學生",
      "同學",
      "羞恥"
    ],
    "description": "HEYZO-0597为HEYZO出品,2014年5月18日发行的無碼成人影片由伊澄知世出演\n集団顔射！食べ尽くされたロリかわ女生徒～淫らな学園の背徳事件簿～ - 伊澄知世",
    "cover_url": "https://picture.yoshiclub.xyz/20241229/951f4040-e4fc-47b9-b0b2-4d9efd211fc6.jpg",
    "background_img": "https://picture.yoshiclub.xyz/20241229/951f4040-e4fc-47b9-b0b2-4d9efd211fc6.jpg",
    "title_play_url": "https://erik7761269084-arch.github.io/-/JAV/player_template.html?series=499",
    "actresses": [
      {
        "name": "伊澄知世",
        "img_url": "https://picture.yoshiclub.xyz/20241216/af03a24a-a314-49bf-ba02-1bd8308ed338.jpg",
        "profile_url": "https://erik7761269084-arch.github.io/-/AV/AVactressDatas.html?series=499&name=伊澄知世"
      }
    ]
  }
}