{
  "episodes": {
    "主线路": "https://t33.cdn2020.com/video/m3u8/2025/09/02/1f0e288e/index.m3u8"
  },
  "seriesInfo": {
    "id": 70709,
    "IDcode": "JUL-065",
    "title": "酒乱ピストン 追撃 絶頂 親戚一同の飲み会、酒に酔った義弟に幾度となくイカされた私―。 白木優子",
    "publish_date": "2019-12-07",
    "type": "有码",
    "company": "MADONNA",
    "genres": [
      "戏剧",
      "成熟的女人",
      "中出",
      "已婚妇女",
      "白天出轨"
    ],
    "description": null,
    "cover_url": "https://cdn4.aiscan.cc/theme/javmenu/images/loading.gif",
    "background_img": null,
    "title_play_url": "https://erik7761269084-arch.github.io/-/JAV/player_template.html?series=70709",
    "actresses": [
      {
        "name": "白木優子",
        "img_url": "https://picture.yoshiclub.xyz/20230928/38b0d51b-9c36-443a-81f1-14c192125f9c.jpg",
        "profile_url": "https://erik7761269084-arch.github.io/-/AV/AVactressDatas.html?series=70709&name=白木優子"
      }
    ]
  }
}