{
  "episodes": {
    "主线路": "https://v2024.bbffsl.com/20250115/spx2gbLt/index.m3u8"
  },
  "seriesInfo": {
    "id": 73894,
    "IDcode": "MIFD-068",
    "title": "18歳激スリムボディー騎乗位の逸材！！AVDebut 加賀美まり",
    "publish_date": "2019-05-13",
    "type": "有码",
    "company": "MOODYZ",
    "genres": [
      "女大学生",
      "女上位",
      "苗条",
      "首次亮相",
      "美少女电影"
    ],
    "description": "",
    "cover_url": "https://fmtu.sl2025p.com/upload/vod/20250116-1/b231d0d41434cb2bd2ff2a92cdff61d9.jpg",
    "background_img": null,
    "title_play_url": "https://erik7761269084-arch.github.io/-/JAV/player_template.html?series=73894",
    "actresses": [
      {
        "name": "加贺美まり",
        "img_url": "",
        "profile_url": "https://erik7761269084-arch.github.io/-/AV/AVactressDatas.html?series=73894&name=加贺美まり"
      }
    ]
  }
}