{
  "episodes": {
    "主线路": "https://v2024.bbffsl.com/20250107/sYmn1LOb/index.m3u8"
  },
  "seriesInfo": {
    "id": 73970,
    "IDcode": "JUY-957",
    "title": "新人 圧倒的クビレと神々しいGカップ 栗栖みなみ 28歳 AVDebut！！",
    "publish_date": "2019-09-07",
    "type": "有码",
    "company": "MADONNA",
    "genres": [
      "精选，综合",
      "成熟的女人",
      "巨乳",
      "已婚妇女",
      "首次亮相",
      "纪录片",
      "素人作品"
    ],
    "description": null,
    "cover_url": "https://cdn4.aiscan.cc/theme/javmenu/images/loading.gif",
    "background_img": null,
    "title_play_url": "https://erik7761269084-arch.github.io/-/JAV/player_template.html?series=73970",
    "actresses": [
      {
        "name": "天沢ゆきね",
        "img_url": "https://picture.yoshiclub.xyz/20240812/a487922b-a365-4c1a-9229-26072d2f6dfb.jpg",
        "profile_url": "https://erik7761269084-arch.github.io/-/AV/AVactressDatas.html?series=73970&name=天沢ゆきね"
      },
      {
        "name": "小田切ジュン",
        "img_url": "",
        "profile_url": "https://erik7761269084-arch.github.io/-/AV/AVactressDatas.html?series=73970&name=小田切ジュン"
      }
    ]
  }
}