{
  "episodes": {
    "主线路": "https://vz-a59c6881-d86.b-cdn.net/88195184-db45-4b15-a4be-691e480ee067/playlist.m3u8",
    "线路2": "https://t30.cdn2020.com/video/m3u8/2025/07/27/a63c678b/index.m3u8"
  },
  "seriesInfo": {
    "id": 7598,
    "IDcode": "MTALL-152",
    "title": "世界上流汗最多的裸體家政婦 ~ 藤沢麗央",
    "publish_date": "2025-03-20",
    "type": "有码",
    "company": "MATERIALL",
    "genres": [
      "後入",
      "劇情",
      "3P・4P",
      "淫亂",
      "巨尻",
      "超爆乳",
      "流汗",
      "乳交",
      "大乳暈",
      "中出",
      "亂交 • 群P",
      "胸控・戀乳癖",
      "女上位",
      "重口味",
      "口交",
      "胖女人",
      "騎乗位",
      "家政婦",
      "兩男一女",
      "慾求不滿",
      "奇聞趣事",
      "巨乳",
      "奇異的",
      "寢取",
      "豐滿"
    ],
    "description": "",
    "cover_url": "https://picture.yoshiclub.xyz/20250313/f19ea577-4e34-476e-b077-a5993fedab47.jpg",
    "background_img": "https://picture.yoshiclub.xyz/20250313/f19ea577-4e34-476e-b077-a5993fedab47.jpg",
    "title_play_url": "https://erik7761269084-arch.github.io/-/JAV/player_template.html?series=7598",
    "actresses": [
      {
        "name": "藤沢麗央",
        "img_url": "https://picture.yoshiclub.xyz/20240218/fb9d5769-7433-4641-9c29-e89c3138a30a.jpg",
        "profile_url": "https://erik7761269084-arch.github.io/-/AV/AVactressDatas.html?series=7598&name=藤沢麗央"
      }
    ]
  }
}