{
  "episodes": {
    "主线路": "https://vip1.slslvip12.com/20221221/jwzqazqp/index.m3u8"
  },
  "seriesInfo": {
    "id": 83136,
    "IDcode": "SDDE-605",
    "title": "パパママ頑張れ！ぬるぬるローションで仲良し家族対抗イキ我慢選手権！合計中出し9発射！",
    "publish_date": "2019-12-12",
    "type": "有码",
    "company": "SOD",
    "genres": [
      "中出",
      "潮吹",
      "乳液",
      "企画",
      "素人作品"
    ],
    "description": null,
    "cover_url": "https://cdn4.aiscan.cc/theme/javmenu/images/loading.gif",
    "background_img": null,
    "title_play_url": "https://erik7761269084-arch.github.io/-/JAV/player_template.html?series=83136",
    "actresses": [
      {
        "name": "天馬唯",
        "img_url": "https://picture.yoshiclub.xyz/20230329/76a01138-1f1d-459f-a7db-d3d2aaf57127.jpg",
        "profile_url": "https://erik7761269084-arch.github.io/-/AV/AVactressDatas.html?series=83136&name=天馬唯"
      },
      {
        "name": "岬梓沙",
        "img_url": "https://picture.yoshiclub.xyz/20230826/2603d214-e17f-4f14-bc42-a088c7bd2afb.jpg",
        "profile_url": "https://erik7761269084-arch.github.io/-/AV/AVactressDatas.html?series=83136&name=岬梓沙"
      },
      {
        "name": "神野雛",
        "img_url": "https://picture.yoshiclub.xyz/20241128/c4a345fb-23a5-4c8a-a479-3b515641e26a.jpg",
        "profile_url": "https://erik7761269084-arch.github.io/-/AV/AVactressDatas.html?series=83136&name=神野雛"
      },
      {
        "name": "星咲凛",
        "img_url": "https://picture.yoshiclub.xyz/compressed/20250707/c8640e75-0917-4989-aaca-b0293d53809a_s.webp",
        "profile_url": "https://erik7761269084-arch.github.io/-/AV/AVactressDatas.html?series=83136&name=星咲凛"
      },
      {
        "name": "久保今日子",
        "img_url": "https://picture.yoshiclub.xyz/GFriends\\Content\\9-Javrave/AI-Fix-久保今日子.jpg",
        "profile_url": "https://erik7761269084-arch.github.io/-/AV/AVactressDatas.html?series=83136&name=久保今日子"
      },
      {
        "name": "蓝井优太",
        "img_url": "",
        "profile_url": "https://erik7761269084-arch.github.io/-/AV/AVactressDatas.html?series=83136&name=蓝井优太"
      },
      {
        "name": "成宫いろは",
        "img_url": "",
        "profile_url": "https://erik7761269084-arch.github.io/-/AV/AVactressDatas.html?series=83136&name=成宫いろは"
      },
      {
        "name": "瀬戸すみれ",
        "img_url": "",
        "profile_url": "https://erik7761269084-arch.github.io/-/AV/AVactressDatas.html?series=83136&name=瀬戸すみれ"
      },
      {
        "name": "高瀬智香",
        "img_url": "",
        "profile_url": "https://erik7761269084-arch.github.io/-/AV/AVactressDatas.html?series=83136&name=高瀬智香"
      }
    ]
  }
}