{
  "episodes": {
    "主线路": "https://1.mysqldata3202s4l.com/20241030/RyLxyVUJ/index.m3u8"
  },
  "seriesInfo": {
    "id": 89383,
    "IDcode": "SUJI-200",
    "title": "思春期の性が淫欲へと誘う 禁断兄妹中出し近親相姦 そら 仲川そら",
    "publish_date": "2023-09-19",
    "type": "有码",
    "company": "妄想族",
    "genres": [
      "高中女生",
      "中出",
      "乱伦",
      "妹妹",
      "美少女电影",
      "单体作品"
    ],
    "description": "",
    "cover_url": "https://cdn4.aiscan.cc/theme/javmenu/images/loading.gif",
    "background_img": null,
    "title_play_url": "https://erik7761269084-arch.github.io/-/JAV/player_template.html?series=89383",
    "actresses": [
      {
        "name": "仲川空",
        "img_url": "https://picture.yoshiclub.xyz/20231128/eb7ce03b-4a45-43d1-a940-82529277e5d2.jpg",
        "profile_url": "https://erik7761269084-arch.github.io/-/AV/AVactressDatas.html?series=89383&name=仲川空"
      }
    ]
  }
}