{
  "episodes": {
    "主线路": "https://t26.cdn2020.com/video/m3u8/2024/02/23/b52c54f8/index.m3u8"
  },
  "seriesInfo": {
    "id": 91405,
    "IDcode": "CKW-006",
    "title": "【FANZA限定】呼び出されるのは、いつも決まって昼休み。なのに…射精は9時間後。しかもそれから直後責め。そして結局、連射セックス 波多野結衣 パンティと生写真付き",
    "publish_date": "2023-12-29",
    "type": "有码",
    "company": "WAAP GROUP",
    "genres": [
      "成熟的女人",
      "中出",
      "无毛",
      "淫语",
      "女上位",
      "荡妇",
      "内衣",
      "M男",
      "手淫",
      "骑乗位",
      "单体作品"
    ],
    "description": null,
    "cover_url": "https://cdn4.aiscan.cc/theme/javmenu/images/loading.gif",
    "background_img": null,
    "title_play_url": "https://erik7761269084-arch.github.io/-/JAV/player_template.html?series=91405",
    "actresses": [
      {
        "name": "波多野结衣",
        "img_url": "https://picture.yoshiclub.xyz/20230122/e7667588-ac34-4d62-810e-bec5f039db3b.jpg",
        "profile_url": "https://erik7761269084-arch.github.io/-/AV/AVactressDatas.html?series=91405&name=波多野结衣"
      }
    ]
  }
}