{
  "episodes": {
    "主线路": "https://a.acgnngca.com/24/06/content_61/517347/2.mp3?m=1331dfae617fc09fe672cf886732415a&t=1767286800"
  },
  "seriesInfo": {
    "id": 3541,
    "IDcode": "折磨血奴.mp3-第2段",
    "title": "折磨血奴.mp3-第2段",
    "publish_date": "2024-06-26",
    "type": "有码",
    "companys": [],
    "genres": [],
    "description": "",
    "cover_url": "https://www.acgxmh.com/statics/images/ext/mp3.png",
    "background_img": "",
    "title_play_url": "https://yunvgong.com/audiobook/player_audio.html?series=折磨血奴.mp3-第2段",
    "actresses": [
      "南征"
    ]
  }
}