{
  "episodes": {
    "主线路": "https://a.acgnngca.com/24/04/content_61/488594/1.mp3?m=69f492a6b46ebc27f839ccf3ff45a4a0&t=1767286800"
  },
  "seriesInfo": {
    "id": 15780,
    "IDcode": "鱿鱼游戏.mp3",
    "title": "鱿鱼游戏.mp3",
    "publish_date": "2024-04-29",
    "type": "有码",
    "companys": [],
    "genres": [],
    "description": "",
    "cover_url": "https://www.acgxmh.com/statics/images/ext/mp3.png",
    "background_img": "",
    "title_play_url": "https://yunvgong.com/audiobook/player_audio.html?series=鱿鱼游戏.mp3",
    "actresses": [
      "芝恩㱏"
    ]
  }
}