{
  "episodes": {
    "主线路": "https://voddadaizi.com:52866/videos/202505/26/68342456fe8f4a822066fc18/5d9be1/index.m3u8"
  },
  "seriesInfo": {
    "id": 7824,
    "title": "被禽獸控制的家~繼父奪走了我和媽媽的一切~[中",
    "publish_date": "",
    "type": "无码",
    "company": "[]",
    "genres": [],
    "description": "",
    "cover_url": "https://voddadaizi.com:52866/videos/202505/26/68342456fe8f4a822066fc18/cover.jpg",
    "background_img": "",
    "title_play_url": "https://yunvgong.com/EcchiAnime/player_template.html?series=7824",
    "actresses": []
  }
}