{
  "episodes": {
    "主线路": "https://jiujiu.one/378351"
  },
  "seriesInfo": {
    "id": 34434,
    "IDcode": "MDX-0263",
    "title": "淫乱性事篇章.爱液与汗液的交织",
    "publish_date": "2024-08-02",
    "type": "无码",
    "company": "麻豆映画传媒",
    "genres": [],
    "description": "",
    "cover_url": "https://picmeta2024.sbs/upload/vod/20230505-1/5f443a9ad8dcf8944b124aef95996941.jpg",
    "background_img": "",
    "title_play_url": "https://erik7761269084-arch.github.io/-/CN_AV/player_template.html?series=MDX-0263",
    "actresses": [
      {
        "name": "梁芸菲",
        "img_url": "https://eve.modelmediaasia.com/model_covers/3M55PG2pswnMJOaOMthp2JnUTx1xPW3Gwe30NZnp_compressed.jpg",
        "profile_url": "https://erik7761269084-arch.github.io/-/AV/AVactressDatas.html?series=8609&name=%E6%A2%81%E8%8A%B8%E8%8F%B2"
      }
    ]
  }
}