{
  "episodes": {
    "主线路": "https://yutubf.lsbbf3.com/20251011/zx1PfPxl/index.m3u8",
    "线路2": "https://lsbbf5.com/20251011/zx1PfPxl/index.m3u8"
  },
  "seriesInfo": {
    "id": 113778,
    "title": "稚嫩女高清纯女高中生3部精选够嫩高颜露脸虽然年纪小技能却很专精",
    "publish_date": "",
    "type": "无码",
    "company": "",
    "genres": [],
    "description": "",
    "cover_url": "https://sbzytpimg1.com:3519/upload/vod/20251012-1/d63892f562b8f8fecb4c684f580a8c7a.jpg",
    "background_img": "",
    "title_play_url": "https://yunvgong.com/CN_SELFIE/player_template.html?series=113778",
    "actresses": []
  }
}