{
  "episodes": {
    "主线路": "https://yutubf.lsbbf3.com/20250925/Kp9e0qEK/index.m3u8"
  },
  "seriesInfo": {
    "id": 128276,
    "title": "诱惑大学生女同天台互摸",
    "publish_date": "",
    "type": "无码",
    "company": "",
    "genres": [],
    "description": "",
    "cover_url": "https://sbzytpimg1.com:3519/upload/vod/20250926-1/6e4c95c639e46db86e03303a8edc1c48.jpg",
    "background_img": "",
    "title_play_url": "https://yunvgong.com/CN_SELFIE/player_template.html?series=128276",
    "actresses": []
  }
}