{
  "episodes": {
    "主线路": "https://lsbbf5.com/20231021/Px3AhoUk/index.m3u8"
  },
  "seriesInfo": {
    "id": 140988,
    "title": "全能家政女仆 特殊的性爱服务1",
    "publish_date": "",
    "type": "无码",
    "company": "",
    "genres": [],
    "description": "",
    "cover_url": "https://sbzytpimg1.com:3519/upload/vod/20231025-34/c4423f0563dc58aea6ae1c2f22e5305d.jpg",
    "background_img": "",
    "title_play_url": "https://yunvgong.com/CN_SELFIE/player_template.html?series=140988",
    "actresses": []
  }
}