{
  "episodes": {
    "主线路": "https://lsbbf5.com/20231021/ouxgNbl8/index.m3u8"
  },
  "seriesInfo": {
    "id": 142022,
    "title": "探花系列-大长腿兼职嫩妹对着镜头深喉舔屌,69扣穴扶着细腰后入",
    "publish_date": "",
    "type": "无码",
    "company": "",
    "genres": [],
    "description": "",
    "cover_url": "https://sbzytpimg1.com:3519/upload/vod/20231025-34/949ddee5e87d23165db4cbdb8b6d7a62.jpg",
    "background_img": "",
    "title_play_url": "https://yunvgong.com/CN_SELFIE/player_template.html?series=142022",
    "actresses": []
  }
}