{
  "episodes": {
    "主线路": "https://voddadaizi.com:52866/videos/202506/19/68541db83ed39b57c0a63d64/6gg37g/index.m3u8"
  },
  "seriesInfo": {
    "id": 151074,
    "title": "Nana邀请性感好友一起对一个幸运的小胖子进行捆绑的。",
    "publish_date": "",
    "type": "无码",
    "company": "",
    "genres": [],
    "description": "",
    "cover_url": "https://voddadaizi.com:52866/videos/202506/19/68541db83ed39b57c0a63d64/cover.jpg",
    "background_img": "",
    "title_play_url": "https://yunvgong.com/CN_SELFIE/player_template.html?series=151074",
    "actresses": []
  }
}