{
  "episodes": {
    "主线路": "https://lsbbf5.com/20241112/5WxtOnu6/index.m3u8"
  },
  "seriesInfo": {
    "id": 164994,
    "title": "【一线天美胸】妹子被爆操。",
    "publish_date": "",
    "type": "无码",
    "company": "",
    "genres": [],
    "description": "",
    "cover_url": "https://sbzytpimg2.com:3519/upload/vod/20241114-1/8a8f80686b6d12e15806d7d4af1aa5eb.jpg",
    "background_img": "",
    "title_play_url": "https://yunvgong.com/CN_SELFIE/player_template.html?series=164994",
    "actresses": []
  }
}