{
  "episodes": {
    "主线路": "https://bf3.qrtuv.com/smv1/202505/09/Cam0P0691F2/video/index.m3u8"
  },
  "seriesInfo": {
    "id": 36524,
    "title": "怀孕孕妇激情大秀，给口交大鸡巴主动上位拿着鸡巴要往逼里塞",
    "publish_date": "",
    "type": "无码",
    "company": "",
    "genres": [],
    "description": "",
    "cover_url": "https://img1.souavzy.org/upload/vod/20250510-1/aefc9dd0665a65b40f7ed9d29a256f2c.jpg",
    "background_img": "",
    "title_play_url": "https://yunvgong.com/CN_SELFIE/player_template.html?series=36524",
    "actresses": []
  }
}