{
  "episodes": {
    "主线路": "https://fqm3u8.com/20241114/YdK7bQ5d/index.m3u8"
  },
  "seriesInfo": {
    "id": 37974,
    "title": "性爱私拍精选大奶眼镜妹无套啪啪做爱骑乘射嘴里吃鸡",
    "publish_date": "",
    "type": "无码",
    "company": "",
    "genres": [],
    "description": "",
    "cover_url": "https://fqjpg4.top/upload/vod/20241229-1/0d38093b94a8c863666eabdff47f8699.jpg",
    "background_img": "",
    "title_play_url": "https://yunvgong.com/CN_SELFIE/player_template.html?series=37974",
    "actresses": []
  }
}