{
  "episodes": {
    "主线路": "https://v1.1bbffvip.com/20240814/OTTRQuKT/index.m3u8",
    "线路2": "https://lsbbf2.com/20230906/kJG4EgqX/index.m3u8"
  },
  "seriesInfo": {
    "id": 60347,
    "title": "嗲嗲的呻吟声听的人心痒痒翘臀黑丝90后小骚货浪叫不止激情",
    "publish_date": "",
    "type": "无码",
    "company": "",
    "genres": [],
    "description": "",
    "cover_url": "https://sbzytpimg1.com:3519/upload/vod/20230910-1/1d19c34e962b84a77914d414c769308b.jpg",
    "background_img": "",
    "title_play_url": "https://yunvgong.com/CN_SELFIE/player_template.html?series=60347",
    "actresses": []
  }
}