{
  "episodes": {
    "主线路": "https://b.v155p.com/20250627/nVj7kUki/index.m3u8",
    "线路2": "https://voddadaizi.com:52866/videos/202501/23/67923a37eab82dc793b9a726/bbeg4e/index.m3u8"
  },
  "seriesInfo": {
    "id": 64394,
    "title": "把精液射在妈妈的菊花里面",
    "publish_date": "",
    "type": "无码",
    "company": "",
    "genres": [],
    "description": "",
    "cover_url": "https://voddadaizi.com:52866/videos/202501/23/67923a37eab82dc793b9a726/cover.jpg",
    "background_img": "",
    "title_play_url": "https://yunvgong.com/CN_SELFIE/player_template.html?series=64394",
    "actresses": []
  }
}