{
  "episodes": {
    "主线路": "https://t33.cdn2020.com/video/m3u8/2025/08/22/6db41344/index.m3u8"
  },
  "seriesInfo": {
    "id": 77860,
    "title": "坐火车跨城去找舅妈五十岁白胖熟女医生插得舅妈叫爸爸爽死了",
    "publish_date": "",
    "type": "无码",
    "company": "",
    "genres": [],
    "description": "",
    "cover_url": "https://tutu1.space/images/2025/08/21/522ac08f0496a8f4721a5875180a4527.jpg",
    "background_img": "",
    "title_play_url": "https://yunvgong.com/CN_SELFIE/player_template.html?series=77860",
    "actresses": []
  }
}