{
  "episodes": {
    "主线路": "https://t30.cdn2020.com/video/m3u8/2025/03/03/6afe5cad/index.m3u8"
  },
  "seriesInfo": {
    "id": 83642,
    "title": "香蕉秀xjx270白嫩长腿少妇",
    "publish_date": "",
    "type": "无码",
    "company": "",
    "genres": [],
    "description": "",
    "cover_url": "https://avxq104.cc/upload/vod/20250303-1/f8fa31dd06a0904864f848191a94b14e.jpg",
    "background_img": "",
    "title_play_url": "https://yunvgong.com/CN_SELFIE/player_template.html?series=83642",
    "actresses": []
  }
}