{
  "episodes": {
    "主线路": "https://t27.cdn2020.com/video/m3u8/2024/04/14/1e50142b/index.m3u8"
  },
  "seriesInfo": {
    "id": 89386,
    "title": "大像传媒之大象号移动诊疗室2-何安汝",
    "publish_date": "",
    "type": "无码",
    "company": "",
    "genres": [],
    "description": "",
    "cover_url": "https://avtdc107.cc/upload/vod/20240415-1/2ab8b8e6404e40e24ea9920e90de52ba.jpg",
    "background_img": "",
    "title_play_url": "https://yunvgong.com/CN_SELFIE/player_template.html?series=89386",
    "actresses": []
  }
}