{
  "episodes": {
    "主线路": "https://t27.cdn2020.com/video/m3u8/2021/09/01/bc82c9a6/index.m3u8"
  },
  "seriesInfo": {
    "id": 96263,
    "title": "MDWP-0003淫欲理发厅-苏娅",
    "publish_date": "",
    "type": "无码",
    "company": "",
    "genres": [],
    "description": "",
    "cover_url": "https://tutu1.space/images/2021/09/01/ca110bf67f8a524e14c5af94b2d8818f.jpg",
    "background_img": "",
    "title_play_url": "https://yunvgong.com/CN_SELFIE/player_template.html?series=96263",
    "actresses": []
  }
}