{
  "episodes": {
    "主线路": "https://krevonix.com/20250108/I58nb8q0/index.m3u8"
  },
  "seriesInfo": {
    "id": 542794,
    "IDcode": "420HHL-049",
    "title": "U.I(22) 素人ホイホイFriends·素人·ハメ撮り·个人撮影·巫女コス·黒髪·巨乳",
    "publish_date": "",
    "type": "有码",
    "companys": [],
    "genres": [
      "巨乳",
      "素人"
    ],
    "description": "",
    "cover_url": "https://tuaskbgnekr.com/20250108/I58nb8q0/1.jpg",
    "background_img": "",
    "title_play_url": "https://yunvgong.com/JAV/player_template.html?series=420HHL-049",
    "actresses": []
  }
}