{
  "episodes": {
    "主线路": "https://krevonix.com/20250716/POq6wouF/index.m3u8"
  },
  "seriesInfo": {
    "id": 575347,
    "IDcode": "702NOSKN-054",
    "title": "18歳Iカップ爆乳素人娘がガチ中出し5P大轮奸で放心イキ！ヲタク女子は体力限界でも大量",
    "publish_date": "",
    "type": "有码",
    "companys": [
      {
        "company": "NOSKINS",
        "company_url": "https://yunvgong.com/JAV/new_company_menu/company_NOSKINS"
      }
    ],
    "genres": [
      "素人",
      "巨乳"
    ],
    "description": "",
    "cover_url": "https://tuaskbgnekr.com/20250716/POq6wouF/1.jpg",
    "background_img": "",
    "title_play_url": "https://yunvgong.com/JAV/player_template.html?series=702NOSKN-054",
    "actresses": []
  }
}