{
  "episodes": {
    "主线路": "https://t33.cdn2020.com/video/m3u8/2025/10/01/bdf29395/index.m3u8",
    "线路2": "https://lsbbf5.com/20251020/AHQgXB7D/index.m3u8",
    "线路3": "https://krevonix.com/20241117/IHr4ltJP/index.m3u8"
  },
  "seriesInfo": {
    "id": 10646,
    "IDcode": "ABF-173",
    "title": "ULTRA HOT SEX 河合あすな発蒸中。興奮は液体を超えてイく。～体の芯まで熱し合うHOTコア・ガズムの全て～ 04",
    "publish_date": "",
    "type": "有码",
    "companys": [
      {
        "company": "蚊香社",
        "company_url": "https://yunvgong.com/JAV/new_company_menu/company_蚊香社",
        "works_count": 1652
      }
    ],
    "genres": [
      "美臀",
      "舔陰",
      "淫亂",
      "中出",
      "美少女電影",
      "丁字裤",
      "按摩・美容店",
      "美少女",
      "絕頂高潮",
      "M男・M女",
      "辣妹/GAL系",
      "色白",
      "企畫",
      "飯店",
      "女優",
      "按摩・物理治療・美容",
      "手指插入",
      "騎乗位",
      "形象俱樂部",
      "美乳",
      "故事集",
      "巨尻",
      "巨乳",
      "流汗",
      "口交",
      "慾求不滿",
      "潮吹",
      "約炮",
      "乳交",
      "女上位",
      "胸控・戀乳癖",
      "後入",
      "性感"
    ],
    "description": "",
    "cover_url": "https://sbzytpimg1.com:3519/upload/vod/20251021-1/50102c2b4c83a30ad0cf7b2be7eebecb.jpg",
    "background_img": "",
    "title_play_url": "https://yunvgong.com/JAV/player_template.html?series=ABF-173",
    "actresses": [
      {
        "name": "河合明日菜",
        "img_url": "https://picture.yoshiclub.xyz/20231020/df251d4e-78ea-4853-b44b-07ca3e9773ad.jpg",
        "profile_url": "https://yunvgong.com/JAV/actressDatas.html?series=333&name=%E6%B2%B3%E5%90%88%E6%98%8E%E6%97%A5%E8%8F%9C"
      }
    ]
  }
}