{
  "episodes": {
    "主线路": "https://krevonix.com/20230724/8fjWhadv/index.m3u8"
  },
  "seriesInfo": {
    "id": 548685,
    "IDcode": "APAK-258",
    "title": "中出し无邪気149cm（Ecup）えりかちゃん ◆色白美巨乳コリコリ乳首◆鬼ハメ激イキ♂ ＃オ",
    "publish_date": "",
    "type": "有码",
    "companys": [
      {
        "company": "AURORA PROJECT ANNEX",
        "company_url": "https://yunvgong.com/JAV/new_company_menu/company_AURORA_PROJECT_ANNEX.html",
        "works_count": 429
      }
    ],
    "genres": [
      "巨乳"
    ],
    "description": "",
    "cover_url": "https://yunvgong.com/cover.jpg",
    "background_img": "",
    "title_play_url": "https://yunvgong.com/JAV/player_template.html?series=APAK-258",
    "actresses": []
  }
}