{
  "episodes": {
    "主线路": "https://t33.cdn2020.com/video/m3u8/2025/11/10/b7653089/index.m3u8",
    "线路2": "https://voddadaizi.com:52866/videos/202502/26/67be97e3cf22ae3e0401f8f8/19cbb1/index.m3u8",
    "线路3": "https://krevonix.com/20240922/wAeyBu1p/index.m3u8"
  },
  "seriesInfo": {
    "id": 12122,
    "IDcode": "APNS-351",
    "title": "「私、引きこもりの同級生とその家族の人たちに凌●され種付けされ続けるの…そう、これから毎日…」 悲劇の孕ませ…快楽に堕ちる巨乳女学生 白石なぎさ",
    "publish_date": "",
    "type": "有码",
    "companys": [
      {
        "company": "AURORA PROJECT ANNEX",
        "company_url": "https://yunvgong.com/JAV/new_company_menu/company_AURORA_PROJECT_ANNEX",
        "works_count": 429
      }
    ],
    "genres": [
      "少女",
      "凌辱",
      "美腳",
      "女學生",
      "口爆",
      "亂交 • 群P",
      "深喉",
      "舔陰",
      "兩男一女",
      "淫亂",
      "中出",
      "美少女電影",
      "劇情",
      "美少女",
      "按摩棒",
      "顏射",
      "69",
      "手指插入",
      "騎乗位",
      "羞恥",
      "輪姦",
      "美乳",
      "美腿",
      "吞精",
      "巨乳",
      "口交",
      "潮吹",
      "魔鬼系",
      "乳交",
      "女上位",
      "多P",
      "後入",
      "JK校服",
      "3P・4P"
    ],
    "description": "",
    "cover_url": "https://voddadaizi.com:52866/videos/202502/26/67be97e3cf22ae3e0401f8f8/cover.jpg",
    "background_img": "",
    "title_play_url": "https://yunvgong.com/JAV/player_template.html?series=APNS-351",
    "actresses": [
      {
        "name": "白石渚",
        "img_url": "https://picture.yoshiclub.xyz/20241104/2bf3dd17-2b68-4fdc-99a0-353abd274001.jpg",
        "profile_url": "https://yunvgong.com/JAV/actressDatas.html?series=126&name=%E7%99%BD%E7%9F%B3%E6%B8%9A"
      }
    ]
  }
}