{
  "episodes": {
    "主线路": "https://xibaocj.com/video/m3u8/202506/18/912ce912ded7/playlist.m3u8"
  },
  "seriesInfo": {
    "id": 102525,
    "IDcode": "BANK-009",
    "title": "和完全看不出好色的姊姊去露天溫泉旅行 瘋狂性愛瘋狂高潮 三好凪",
    "publish_date": "2024-07-17",
    "type": "有码",
    "companys": [
      {
        "company": "ま○こ銀行",
        "company_url": "https://yunvgong.com/JAV/new_company_menu/company_ま○こ銀行.html",
        "works_count": 154
      }
    ],
    "genres": [],
    "description": "",
    "cover_url": "https://yunvgong.com/cover.jpg",
    "background_img": "",
    "title_play_url": "https://yunvgong.com/JAV/player_template.html?series=BANK-009",
    "actresses": []
  }
}