{
  "episodes": {
    "主线路": "https://bf3.qrtuv.com/smv1/202508/30/EqbbMpJ0xd2/video/index.m3u8"
  },
  "seriesInfo": {
    "id": 556952,
    "IDcode": "BLK-347",
    "title": "很久以前欺负我的青梅竹马，一次分娩健康遭遇！ !!理所当然地，我强迫制作成为情妇并多次调用它并射精性爱 Miyu Amano - 天野美优",
    "publish_date": "",
    "type": "有码",
    "companys": [
      {
        "company": "KIRAKIRA",
        "company_url": "https://yunvgong.com/JAV/new_company_menu/company_KIRAKIRA.html",
        "works_count": 390
      }
    ],
    "genres": [],
    "description": "",
    "cover_url": "https://img1.souavzy.org/upload/vod/20250831-1/b7420003960a47027a05183f55c4324f.jpg",
    "background_img": "",
    "title_play_url": "https://yunvgong.com/JAV/player_template.html?series=BLK-347",
    "actresses": []
  }
}