{
  "episodes": {
    "主线路": "https://vip8.3sybf.com/20221206/cYVtdhkT/index.m3u8"
  },
  "seriesInfo": {
    "id": 522032,
    "IDcode": "BMW01-3044",
    "title": "位女他优他",
    "publish_date": "",
    "type": "有码",
    "companys": [],
    "genres": [],
    "description": "",
    "cover_url": "https://ll.lasha250923.top/upload/vod/20221207-1/fefc44ba824e544cf360313ad09e9754.jpg",
    "background_img": "",
    "title_play_url": "https://yunvgong.com/JAV/player_template.html?series=BMW01-3044",
    "actresses": []
  }
}