{
  "episodes": {
    "主线路": "https://video36.bpzy1.com/video/20221105/90c148e814df6d568208fddd2c740399/index.m3u8"
  },
  "seriesInfo": {
    "id": 579101,
    "IDcode": "BUBB-121",
    "title": "阶段女子校生 やっぱり美脚女子校生の制服のスカートの中が覗きたい 编",
    "publish_date": "",
    "type": "有码",
    "companys": [],
    "genres": [
      "抄底"
    ],
    "description": "",
    "cover_url": "https://pic36.anzise.com/pic/20221105/90c148e814df6d568208fddd2c740399/1.jpg",
    "background_img": "",
    "title_play_url": "https://yunvgong.com/JAV/player_template.html?series=BUBB-121",
    "actresses": []
  }
}