{
  "episodes": {
    "主线路": "https://vostrely.com/20230411/ISrmZ7tO/index.m3u8"
  },
  "seriesInfo": {
    "id": 556103,
    "IDcode": "CARIB-041123-001",
    "title": "彼氏のお愿い！ガチ介护プレイ ～ノリノリナースの歓喜の潮吹き～杉浦花音",
    "publish_date": "",
    "type": "无码",
    "companys": [
      {
        "company": "加勒比系",
        "company_url": "https://yunvgong.com/JAV/new_company_menu/company_加勒比系"
      }
    ],
    "genres": [
      "素人",
      "高清画质",
      "无码"
    ],
    "description": "",
    "cover_url": "https://tuaskbgnekr.com/20230411/YSsPdmHT/1.jpg",
    "background_img": "",
    "title_play_url": "https://yunvgong.com/JAV/player_template.html?series=CARIB-041123-001",
    "actresses": []
  }
}