{
  "episodes": {
    "主线路": "https://v3-2.lbv3lb2025.com/20231123/9uX2Sl03/index.m3u8"
  },
  "seriesInfo": {
    "id": 549555,
    "IDcode": "DOCP-069",
    "title": "うるさいイビキを止めようと何をやっても效果なし…腹いせに颜面骑乘位で塞いでやると吐息で擦れるアソコが気",
    "publish_date": "",
    "type": "有码",
    "companys": [],
    "genres": [],
    "description": "",
    "cover_url": "https://yunvgong.com/cover.jpg",
    "background_img": "",
    "title_play_url": "https://yunvgong.com/JAV/player_template.html?series=DOCP-069",
    "actresses": []
  }
}