{
  "episodes": {
    "主线路": "https://t27.cdn2020.com/video/m3u8/2022/06/25/9a806ff9/index.m3u8"
  },
  "seriesInfo": {
    "id": 218491,
    "IDcode": "FAX-339",
    "title": "我想要一个男人的夜晚",
    "publish_date": "",
    "type": "有码",
    "company": null,
    "genres": [],
    "description": "",
    "cover_url": "https://tutu1.space/images/2022/06/25/aa8a2289a581d4ac69f448c61824020d.jpg",
    "background_img": "",
    "title_play_url": "https://yunvgong.com/JAV/player_template.html?series=FAX-339",
    "actresses": []
  }
}