{
  "episodes": {
    "主线路": "https://lsbbf5.com/20231012/XZVnLPVs/index.m3u8"
  },
  "seriesInfo": {
    "id": 553708,
    "IDcode": "FC2-PPV-1247291",
    "title": "A これで见纳め-早期终了した幻の19歳が再び登场--人生初イキの后は本気汁MAX！最后は立ちバックで生中出し-【个人撮影】",
    "publish_date": "",
    "type": "有码",
    "companys": [
      {
        "company": "FC2",
        "company_url": "https://yunvgong.com/JAV/new_company_menu/company_FC2.html",
        "works_count": 15467
      }
    ],
    "genres": [
      "嫩妹"
    ],
    "description": "",
    "cover_url": "https://fm.sl25914.com/upload/vod/20230905-1/374bf2a336c5368187e5e544d9a87a96.jpg",
    "background_img": "",
    "title_play_url": "https://yunvgong.com/JAV/player_template.html?series=FC2-PPV-1247291",
    "actresses": []
  }
}