{
  "episodes": {
    "主线路": "https://v1.1bbffvip.com/20220810/Gl0WMn5q/index.m3u8"
  },
  "seriesInfo": {
    "id": 576463,
    "IDcode": "FC2PPV-827389",
    "title": "完全初撮り-制服生ハメ-普通すぎる18歳奈",
    "publish_date": "",
    "type": null,
    "company": "FC2",
    "genres": [],
    "description": "",
    "cover_url": "http://15.155250922.com/upload/vod/2022/09/rn2cnvhmwxv.jpg",
    "background_img": "",
    "title_play_url": "https://yunvgong.com/JAV/player_template.html?series=FC2PPV-827389",
    "actresses": []
  }
}