{
  "episodes": {
    "主线路": "https://www.lbbf9.com/20191029/yTvxO4Ts/index.m3u8"
  },
  "seriesInfo": {
    "id": 575513,
    "IDcode": "FC2PPV-958182",
    "title": "（モザイク有り）J★制服リフレの激カ第03集",
    "publish_date": "",
    "type": null,
    "company": "FC2",
    "genres": [],
    "description": "",
    "cover_url": "https://fm.lbtup2025.com/upload/vod/2019/11-08/05/pz5ovekd4qz0518pz5ovekd4qz3514190.jpg",
    "background_img": "",
    "title_play_url": "https://yunvgong.com/JAV/player_template.html?series=FC2PPV-958182",
    "actresses": []
  }
}