{
  "episodes": {
    "主线路": "https://t33.cdn2020.com/video/m3u8/2025/09/05/07af8ffa/index.m3u8"
  },
  "seriesInfo": {
    "id": 185600,
    "IDcode": "FC2PPV-3288131",
    "title": "经济困难无法独自维持生计最终决定拍片",
    "publish_date": "",
    "type": "有码",
    "company": "[]",
    "genres": [],
    "description": "",
    "cover_url": "https://tutu1.space/images/2025/09/05/c5956293eb442840e8e6cb7b9d11cdbe.jpg",
    "background_img": "",
    "title_play_url": "https://yunvgong.com/JAV/player_template.html?series=FC2PPV-3288131",
    "actresses": []
  }
}