{
  "episodes": {
    "主线路": "https://v2024.bbffsl.com/20241219/MzbcDEMD/index.m3u8"
  },
  "seriesInfo": {
    "id": 75215,
    "IDcode": "GZAP-019",
    "title": "ブレインクラッシュ催●連鎖～パンデミック連鎖催●で生意気姉妹を俺の大好きなハーレム奴●にしてやった～",
    "publish_date": "2020-03-13",
    "type": "有码",
    "company": "MILK",
    "genres": [],
    "description": "",
    "cover_url": "https://fmtu.sl2025p.com/upload/vod/20241220-1/a715aaa4d1537bd7172a205daa0123cd.jpg",
    "background_img": "",
    "title_play_url": "https://yunvgong.com/JAV/player_template.html?series=GZAP-019",
    "actresses": []
  }
}