{
  "episodes": {
    "主线路": "https://t27.cdn2020.com/video/m3u8/2021/11/15/81a2a172/index.m3u8"
  },
  "seriesInfo": {
    "id": 214472,
    "IDcode": "HBAD-199",
    "title": "隔壁美丽的年轻妻子-愛内希",
    "publish_date": "",
    "type": "有码",
    "companys": [
      {
        "company": "HIBINO",
        "company_url": "https://yunvgong.com/JAV/new_company_menu/company_HIBINO.html",
        "works_count": 417
      }
    ],
    "genres": [],
    "description": "",
    "cover_url": "https://yunvgong.com/cover.jpg",
    "background_img": "",
    "title_play_url": "https://yunvgong.com/JAV/player_template.html?series=HBAD-199",
    "actresses": []
  }
}