{
  "episodes": {
    "主线路": "https://v1.1bbffvip.com/20230206/TGoxoDVQ/index.m3u8"
  },
  "seriesInfo": {
    "id": 578830,
    "IDcode": "HUNT-460",
    "title": "学校帰りに突然の雷雨で我が家に雨宿りしに来た娘とそのクラスメイト达",
    "publish_date": "",
    "type": "有码",
    "companys": [
      {
        "company": "TMA",
        "company_url": "https://yunvgong.com/JAV/new_company_menu/company_TMA",
        "works_count": 5163
      }
    ],
    "genres": [],
    "description": "",
    "cover_url": "https://yunvgong.com/cover.jpg",
    "background_img": "",
    "title_play_url": "https://yunvgong.com/JAV/player_template.html?series=HUNT-460",
    "actresses": []
  }
}