{
  "episodes": {
    "主线路": "https://t27.cdn2020.com/video/m3u8/2020/12/19/64f6108e/index.m3u8"
  },
  "seriesInfo": {
    "id": 75675,
    "IDcode": "HZGD-136",
    "title": "出張先相部屋-三船かれん",
    "publish_date": "",
    "type": "有码",
    "company": "[]",
    "genres": [],
    "description": "",
    "cover_url": "https://tutu1.space/images/2020/12/19/c91f818b0e292853da7bfa5a764d4309.jpg",
    "background_img": "",
    "title_play_url": "https://yunvgong.com/JAV/player_template.html?series=HZGD-136",
    "actresses": [
      {
        "name": "三船かれん",
        "img_url": "https://upload.xchina.io/default/model.jpg",
        "profile_url": "https://yunvgong.com/JAV/actressDatas.html?series=3691&name=%E4%B8%89%E8%88%B9%E3%81%8B%E3%82%8C%E3%82%93"
      }
    ]
  }
}