{
  "episodes": {
    "主线路": "https://bf3.qrtuv.com/smv1/202409/23/7wFLyL5iRQ1/video/index.m3u8",
    "线路2": "https://bf3.qrtuv.com/smv1/202507/20/3xEWC46ueF2/video/index.m3u8",
    "线路3": "https://t27.cdn2020.com/video/m3u8/2024/06/17/62d659d3/index.m3u8"
  },
  "seriesInfo": {
    "id": 14473,
    "IDcode": "JUQ-710",
    "title": "妻子妊娠中-推川百合",
    "publish_date": "",
    "type": "有码",
    "company": "MADONNA",
    "genres": [],
    "description": "",
    "cover_url": "/upload/vod/20240819-1/8f087ce1983145ef3e2b39e9944d410e.jpg",
    "background_img": "",
    "title_play_url": "https://yunvgong.com/JAV/player_template.html?series=JUQ-710",
    "actresses": [
      {
        "name": "推川悠里",
        "img_url": "https://picture.yoshiclub.xyz/20231211/a1703542-04e6-494e-b31e-5f4d4b30ef61.jpg",
        "profile_url": "https://yunvgong.com/JAV/actressDatas.html?series=183&name=%E6%8E%A8%E5%B7%9D%E6%82%A0%E9%87%8C"
      },
      {
        "name": "ニック",
        "img_url": "https://upload.xchina.io/default/model.jpg",
        "profile_url": "https://yunvgong.com/JAV/actressDatas.html?series=2999&name=%E3%83%8B%E3%83%83%E3%82%AF"
      }
    ]
  }
}