{
  "episodes": {
    "主线路": "https://t33.cdn2020.com/video/m3u8/2025/08/02/4df59228/index.m3u8"
  },
  "seriesInfo": {
    "id": 61208,
    "IDcode": "KOJA-024",
    "title": "面接に来たFカップの巨乳レイヤー！？テスト撮影にもノリノリで即日オフィスハメ、ノリで中出し「え…出すの…」 月野はなび",
    "publish_date": "",
    "type": "有码",
    "companys": [],
    "genres": [
      "巨乳"
    ],
    "description": "",
    "cover_url": "https://lust103.cc/upload/vod/20250806-1/e5db4d09c9b270a90b5fe03194727cc0.jpg",
    "background_img": "",
    "title_play_url": "https://yunvgong.com/JAV/player_template.html?series=KOJA-024",
    "actresses": []
  }
}