{
  "episodes": {
    "主线路": "https://t27.cdn2020.com/video/m3u8/2023/03/20/488d1a56/index.m3u8",
    "线路2": "https://lsbbf5.com/20250402/t6Gddf7f/index.m3u8",
    "线路3": "https://v2025.fhbbff.com/20250410/0E5dJGr6/index.m3u8",
    "线路4": "https://yutubf.lsbbf3.com/20250402/t6Gddf7f/index.m3u8",
    "线路5": "https://v2024.sysybf.com/20250409/1M6BgnmF/index.m3u8",
    "线路6": "https://v5.lbv325627.com/20250409/1M6BgnmF/index.m3u8"
  },
  "seriesInfo": {
    "id": 68902,
    "IDcode": "MIAA-783",
    "title": "中年爸爸的阴部按摩-新井リマ",
    "publish_date": "",
    "type": "有码",
    "companys": [
      {
        "company": "MOODYZ",
        "company_url": "https://yunvgong.com/JAV/new_company_menu/company_MOODYZ",
        "works_count": 2545
      }
    ],
    "genres": [
      "戏剧",
      "乱伦",
      "白天出轨",
      "舔阴",
      "中出",
      "制服",
      "单体作品"
    ],
    "description": "",
    "cover_url": "https://lust103.cc/upload/vod/20250512-4/3e897b64cc48e11db4fa5b791ce27b36.jpg",
    "background_img": "",
    "title_play_url": "https://yunvgong.com/JAV/player_template.html?series=MIAA-783",
    "actresses": []
  }
}