{
  "episodes": {
    "主线路": "https://t33.cdn2020.com/video/m3u8/2025/08/21/062388be/index.m3u8"
  },
  "seriesInfo": {
    "id": 3475,
    "IDcode": "MMBF-001",
    "title": "長靴誘惑 腳下臣服的極致快感 ~ 尾崎惠梨香",
    "publish_date": "2025-08-15",
    "type": "有码",
    "company": "MARRION",
    "genres": [],
    "description": "MMBF-001为MARRION出品,2025年8月15日发行的有碼成人影片由尾崎惠梨香出演\n聞著姊的腳香就能讓你爽到不行！別裝了，你在我面前啥地位都沒有，快跪下來舔姊的腳！這雙長靴悶得熱呼呼的腳丫子，就是給你的頂級獎賞！沉醉在尾崎惠梨香的足控世界，91分鐘讓你欲罷不能！",
    "cover_url": "https://picture.yoshiclub.xyz/compressed/20250818/20250818090342550550_13019_thumbnail.webp",
    "background_img": "https://picture.yoshiclub.xyz/compressed/20250818/20250818090342550550_13019_s.webp",
    "title_play_url": "https://yunvgong.com/JAV/player_template.html?series=MMBF-001",
    "actresses": [
      {
        "name": "尾崎惠梨香",
        "img_url": "https://picture.yoshiclub.xyz/20231017/f57001d3-f004-4808-b92a-9368d0918b62.jpg",
        "profile_url": "https://yunvgong.com/JAV/actressDatas.html?series=88&name=%E5%B0%BE%E5%B4%8E%E6%83%A0%E6%A2%A8%E9%A6%99"
      }
    ]
  }
}