{
  "episodes": {
    "主线路": "https://1.mysqldata3202s4l.com/20241008/84FYNiR4/index.m3u8",
    "线路2": "https://lsbbf5.com/20241009/ZFfpNdX7/index.m3u8",
    "线路3": "https://voddadaizi.com:52866/videos/202503/28/67e585b14e7d663df43d0ddb/b25g29/index.m3u8",
    "线路4": "https://voddadaizi.com:52866/videos/202501/18/678a17ddac813dc779d9600a/677e0f/index.m3u8"
  },
  "seriesInfo": {
    "id": 13922,
    "IDcode": "MUDR-263",
    "title": "自從那天起... 穿着制服的漂亮女孩在束縛訓練中被射精 乃々瀬あい",
    "publish_date": "",
    "type": "有码",
    "companys": [
      {
        "company": "無垢",
        "company_url": "https://yunvgong.com/JAV/new_company_menu/company_無垢.html",
        "works_count": 500
      }
    ],
    "genres": [
      "凌辱",
      "性虐癖",
      "拘束・拷問",
      "蕩婦",
      "SM",
      "亂交 • 群P",
      "淫亂",
      "中出",
      "美少女電影",
      "劇情",
      "調教",
      "美少女",
      "按摩棒",
      "絕頂高潮",
      "緊縛",
      "飯店",
      "苗條",
      "美乳",
      "巨乳",
      "胸控・戀乳癖",
      "放尿",
      "JK校服",
      "性感",
      "跳蛋"
    ],
    "description": "",
    "cover_url": "https://sbzytpimg1.com:3519/upload/vod/20241010-1/144d9cc3345465ee52e22e8e3e907de0.jpg",
    "background_img": "",
    "title_play_url": "https://yunvgong.com/JAV/player_template.html?series=MUDR-263",
    "actresses": [
      {
        "name": "乃々瀬あい",
        "img_url": "https://picture.yoshiclub.xyz/20240417/1797904e-7ba5-451b-894f-bd9e97ff118f.jpg",
        "profile_url": "https://yunvgong.com/JAV/actressDatas.html?series=501&name=%E4%B9%83%E3%80%85%E7%80%AC%E3%81%82%E3%81%84"
      }
    ]
  }
}