{
  "episodes": {
    "主线路": "https://vostrely.com/20230613/kJybVnoQ/index.m3u8"
  },
  "seriesInfo": {
    "id": 55663,
    "IDcode": "N0414",
    "title": "女子アナ輪カン業界肉便器",
    "publish_date": "2009-03-13",
    "type": "无码",
    "companys": [],
    "genres": [
      "素人",
      "无码"
    ],
    "description": "",
    "cover_url": "https://tuaskbgnekr.com/20230613/5Eox5q42/1.jpg",
    "background_img": "",
    "title_play_url": "https://yunvgong.com/JAV/player_template.html?series=N0414",
    "actresses": []
  }
}