{
  "episodes": {
    "主线路": "https://t27.cdn2020.com/video/m3u8/2023/03/30/42f3a570/index.m3u8",
    "线路2": "https://voddadaizi.com:52866/videos/202505/21/682dbe5b7e1ae1e49a49ca47/dd9ege/index.m3u8",
    "线路3": "https://v1.1bbffvip.com/20240220/SYd01zal/index.m3u8",
    "线路4": "https://krevonix.com/20231105/QddNB4j8/index.m3u8"
  },
  "seriesInfo": {
    "id": 107309,
    "IDcode": "PRED-465",
    "title": "舞雪先生-伊藤舞雪",
    "publish_date": "",
    "type": "无码",
    "companys": [
      {
        "company": "PREMIUM",
        "company_url": "https://yunvgong.com/JAV/new_company_menu/company_PREMIUM.html",
        "works_count": 951
      }
    ],
    "genres": [
      "巨乳",
      "单体作品",
      "乳交",
      "无码破解",
      "4K",
      "中出",
      "女教师",
      "无码",
      "素人",
      "白天出轨"
    ],
    "description": "",
    "cover_url": "https://voddadaizi.com:52866/videos/202505/21/682dbe5b7e1ae1e49a49ca47/cover.jpg",
    "background_img": "",
    "title_play_url": "https://yunvgong.com/JAV/player_template.html?series=PRED-465",
    "actresses": [
      {
        "name": "伊藤舞雪",
        "img_url": "https://picture.yoshiclub.xyz/20231105/8926413a-85ad-46dd-897e-24b65bcb4d3c.jpg",
        "profile_url": "https://yunvgong.com/JAV/actressDatas.html?series=233&name=%E4%BC%8A%E8%97%A4%E8%88%9E%E9%9B%AA"
      }
    ]
  }
}