{
  "episodes": {
    "主线路": "https://t26.cdn2020.com/video/m3u8/2023/05/28/e74890cc/index.m3u8"
  },
  "seriesInfo": {
    "id": 77623,
    "IDcode": "SSIS-162",
    "title": "未公開映像収録のプレミアムエディション！ディレクターズカット版 彩花とハメまくりイチャイチャ同棲しようよ 河北彩花 （ブルーレイディスク） （BOD）",
    "publish_date": "2021-07-25",
    "type": "有码",
    "company": "S1",
    "genres": [],
    "description": "",
    "cover_url": "",
    "background_img": "",
    "title_play_url": "https://erik7761269084-arch.github.io/-/JAV/player_template.html?series=SSIS-162",
    "actresses": [
      {
        "name": "河北彩花",
        "img_url": "https://picture.yoshiclub.xyz/20230914/df5943a4-bf36-4bdf-ab41-60918d7e13b3.jpg",
        "profile_url": "https://erik7761269084-arch.github.io/-/JAV/JAV_actressDatas.html?series=182&name=%E6%B2%B3%E5%8C%97%E5%BD%A9%E8%8A%B1"
      }
    ]
  }
}