{
  "episodes": {
    "主线路": "https://t26.cdn2020.com/video/m3u8/2023/10/27/ef516cec/index.m3u8"
  },
  "seriesInfo": {
    "id": 18441,
    "IDcode": "SSIS-902",
    "title": "蘿莉面孔與大量性愛 最接近真實的性愛之旅",
    "publish_date": "2023-10-11",
    "type": "有码",
    "company": "S1",
    "genres": [],
    "description": "SSIS-902为S1出品,2023年10月11日发行的有碼成人影片由望月蕾出演\n這是一個過夜約會項目，深入了解「望月つぼみ」的私生活，她天真無邪且充滿魅力。 逛街或吃美食的時候，就像個小女孩一樣開朗可愛……但是一進酒店，氣氛就完全變了，變成了一張充滿性感的女人臉。 熱情的舌吻彷彿釋放了壓抑的東西……互相嬉戲，進行著激烈的性愛。 只要時間允許，她就叫喊，只要時間允許，她就一遍遍地叫喊……她是個身體雖小，性慾卻無窮無盡的怪物！ 一個平常都有如此露骨性愛的超級好色的女孩會出來！\n這是一個過夜約會項目，深入了解「望月つぼみ」的私生活，她天真無邪且充滿魅力。 逛街或吃美食的時候，就像個小女孩一樣開朗可愛……但是一進酒店，氣氛就完全變了，變成了一張充滿性感的女人臉。 熱情的舌吻彷彿釋放了壓抑的東西……互相嬉戲，進行著激烈的性愛。 只要時間允許，她就叫喊，只要時間允許，她就一遍遍地叫喊……她是個身體雖小，性慾卻無窮無盡的怪物！ 一個平常都有如此露骨性愛的超級好色的女孩會出來！",
    "cover_url": "https://picture.yoshiclub.xyz/20231007/38a03c7a-7eee-444d-95e0-e8cac2f3aa2a.jpg",
    "background_img": "https://picture.yoshiclub.xyz/20231007/38a03c7a-7eee-444d-95e0-e8cac2f3aa2a.jpg",
    "title_play_url": "https://erik7761269084-arch.github.io/-/JAV/player_template.html?series=SSIS-902",
    "actresses": [
      {
        "name": "望月蕾",
        "img_url": "https://picture.yoshiclub.xyz/20231007/e883678f-6dbb-4ab7-8a93-8fd3558d5370.jpg",
        "profile_url": "https://erik7761269084-arch.github.io/-/JAV/JAV_actressDatas.html?series=55&name=%E6%9C%9B%E6%9C%88%E8%95%BE"
      }
    ]
  }
}