{
  "episodes": {
    "主线路": "https://v1.1bbffvip.com/20240215/Ha0M6Xtq/index.m3u8"
  },
  "seriesInfo": {
    "id": 579497,
    "IDcode": "TEND-007",
    "title": "妻が出て行きました…そして娘が妻になりました… _ 佐久良咲希",
    "publish_date": "",
    "type": "有码",
    "companys": [
      {
        "company": "Tender",
        "company_url": "https://yunvgong.com/JAV/new_company_menu/company_Tender"
      }
    ],
    "genres": [],
    "description": "",
    "cover_url": "http://15.155250922.com/upload/vod/20240216/h_1753tend007pl.jpg!320x216.jpg",
    "background_img": "",
    "title_play_url": "https://yunvgong.com/JAV/player_template.html?series=TEND-007",
    "actresses": []
  }
}