{
  "episodes": {
    "主线路": "https://jkunnzyx.com/20230304/L2dGGJiF/index.m3u8"
  },
  "seriesInfo": {
    "id": 595065,
    "IDcode": "UMSO-258",
    "title": "丈夫打来电话时正在偷情！！被出轨对象强迫接起电话的人妻拼命压抑喘息声， 却因为升级的激烈行为而兴奋度MAX！",
    "publish_date": "",
    "type": "有码",
    "companys": [
      {
        "company": "K.M.P",
        "company_url": "https://yunvgong.com/JAV/new_company_menu/company_KMP",
        "works_count": 1270
      }
    ],
    "genres": [
      "人妻"
    ],
    "description": "",
    "cover_url": "https://yunvgong.com/cover.jpg",
    "background_img": "",
    "title_play_url": "https://yunvgong.com/JAV/player_template.html?series=UMSO-258",
    "actresses": []
  }
}