{
  "episodes": {
    "主线路": "https://t30.cdn2020.com/video/m3u8/2025/07/27/af80a898/index.m3u8",
    "线路2": "https://v1.1bbffvip.com/20221129/0sgEbDGO/index.m3u8"
  },
  "seriesInfo": {
    "id": 95039,
    "IDcode": "URE-052",
    "title": "经典漫改巨乳人妻深田咏美的选择明明喜欢的是前辈却不知不觉成为了老师的母猪肉便器",
    "publish_date": "",
    "type": "有码",
    "company": "[]",
    "genres": [
      "巨乳",
      "已婚妇女",
      "成熟的女人",
      "人妻",
      "白天出轨"
    ],
    "description": "",
    "cover_url": "/upload/vod/20250801-1/2bd27bf260485d1eabd87469d8e39a54.jpg",
    "background_img": "",
    "title_play_url": "https://yunvgong.com/JAV/player_template.html?series=URE-052",
    "actresses": []
  }
}