{
  "episodes": {
    "主线路": "https://v1.1bbffvip.com/20231210/AWkFrHN6/index.m3u8",
    "线路2": "https://t26.cdn2020.com/video/m3u8/2023/05/21/aa89cd4a/index.m3u8"
  },
  "seriesInfo": {
    "id": 168215,
    "IDcode": "VEC-586",
    "title": "见面就开始的中出SEX-翔田千里",
    "publish_date": "",
    "type": "有码",
    "company": "[]",
    "genres": [],
    "description": "",
    "cover_url": "https://avtdc107.cc/upload/vod/20240118-7/147c90f0a694130bf3aae4ee073f0c5e.jpg",
    "background_img": "",
    "title_play_url": "https://yunvgong.com/JAV/player_template.html?series=VEC-586",
    "actresses": []
  }
}