{
  "episodes": {
    "主线路": "https://lsbbf5.com/20250802/AfWn7J19/index.m3u8",
    "线路2": "https://v2025.fhbbff.com/20250809/kwSnK7l6/index.m3u8",
    "线路3": "https://v5.lbv325627.com/20250809/KjLaGNNc/index.m3u8",
    "线路4": "https://krevonix.com/20250709/nBsnmqwJ/index.m3u8"
  },
  "seriesInfo": {
    "id": 588354,
    "IDcode": "WA-552",
    "title": "素人妻搭讪全部现场内射5小时 名流人妻 98 素人",
    "publish_date": "",
    "type": "有码",
    "companys": [],
    "genres": [
      "人妻",
      "素人"
    ],
    "description": "",
    "cover_url": "https://tuaskbgnekr.com/20250709/nBsnmqwJ/1.jpg",
    "background_img": "",
    "title_play_url": "https://yunvgong.com/JAV/player_template.html?series=WA-552",
    "actresses": []
  }
}