{
  "episodes": {
    "主线路": "https://krevonix.com/20240918/JI82cluF/index.m3u8"
  },
  "seriesInfo": {
    "id": 560376,
    "IDcode": "YST-295",
    "title": "下品だとか上品だとか関系なく、エグイくらい天海さんを弄びたい",
    "publish_date": "",
    "type": "有码",
    "companys": [
      {
        "company": "TMA",
        "company_url": "https://yunvgong.com/JAV/new_company_menu/company_TMA"
      }
    ],
    "genres": [],
    "description": "",
    "cover_url": "https://tuaskbgnekr.com/20240918/JI82cluF/1.jpg",
    "background_img": "",
    "title_play_url": "https://yunvgong.com/JAV/player_template.html?series=YST-295",
    "actresses": []
  }
}